xsmeteo/__init__.py
xsmeteo/py.typed
xsmeteo/client/__init__.py
xsmeteo/client/async_client.py
xsmeteo/client/sync_client.py
xsmeteo/core/__init__.py
xsmeteo/core/config.py
xsmeteo/core/http_base.py
xsmeteo/core/rate_limiter.py
xsmeteo/exceptions/__init__.py
xsmeteo/exceptions/errors.py
xsmeteo/models/__init__.py
xsmeteo/models/air_quality.py
xsmeteo/models/base.py
xsmeteo/models/climate.py
xsmeteo/models/common.py
xsmeteo/models/elevation.py
xsmeteo/models/ensemble.py
xsmeteo/models/flood.py
xsmeteo/models/forecast.py
xsmeteo/models/geocoding.py
xsmeteo/models/historical.py
xsmeteo/models/marine.py
xsmeteo/services/__init__.py
xsmeteo/services/air_quality.py
xsmeteo/services/climate.py
xsmeteo/services/common.py
xsmeteo/services/elevation.py
xsmeteo/services/ensemble.py
xsmeteo/services/flood.py
xsmeteo/services/forecast.py
xsmeteo/services/geocoding.py
xsmeteo/services/historical.py
xsmeteo/services/marine.py
xsmeteo-0.1.0.dist-info/METADATA
xsmeteo-0.1.0.dist-info/WHEEL
xsmeteo-0.1.0.dist-info/licenses/LICENSE
xsmeteo-0.1.0.dist-info/RECORD
