Metadata-Version: 2.4
Name: xsmeteo
Version: 0.1.0
Summary: High-performance, strictly typed Python wrapper for Open-Meteo API
License-File: LICENSE
Requires-Python: >=3.12
Requires-Dist: httpx>=0.27.0
Requires-Dist: msgspec>=0.18.6
